Metadata-Version: 2.1
Name: hunterk
Version: 0.0.1
Summary: Package to get Content data from wikipedia and IMDB
Home-page: https://github.com/hunterkempf/ContentData
Author: Hunter Kempf
Author-email: hunterkempf@gmail.com
License: UNKNOWN
Platform: UNKNOWN
Classifier: Programming Language :: Python :: 3
Classifier: License :: OSI Approved :: MIT License
Classifier: Operating System :: OS Independent
Requires-Python: >=3.6
